Metadata-Version: 1.1
Name: armistice
Version: 0.0.0
Summary: Hardware private key storage for next-generation cryptography
Home-page: https://github.com/iqlusioninc/armistice/blob/develop/README.md
Author: Tony Arcieri
Author-email: tony@iqlusion.io
License: Apache Software License
Keywords: encryption,signing
Platform: UNKNOWN
Classifier: Development Status :: 2 - Pre-Alpha
Classifier: Intended Audience :: Developers
